z3c/template/README.rst
z3c/template/__init__.py
z3c/template/interfaces.py
z3c/template/meta.zcml
z3c/template/template.py
z3c/template/tests.py
z3c/template/zcml.py
z3c/template/zcml.rst
z3c_template-5.0.dist-info/LICENSE.txt
z3c_template-5.0.dist-info/METADATA
z3c_template-5.0.dist-info/WHEEL
z3c_template-5.0.dist-info/top_level.txt
z3c_template-5.0.dist-info/RECORD
