Metadata-Version: 2.2
Name: z3c.template
Version: 5.0
Summary: A package implementing advanced Page Template patterns.
Home-page: https://github.com/zopefoundation/z3c.template
Author: Roger Ineichen and the Zope Community
Author-email: zope-dev@zope.dev
License: ZPL-2.1
Keywords: zope3 template layout zpt pagetemplate
Classifier: Development Status :: 5 - Production/Stable
Classifier: Environment :: Web Environment
Classifier: Intended Audience :: Developers
Classifier: License :: OSI Approved :: Zope Public License
Classifier: Programming Language :: Python :: 3
Classifier: Programming Language :: Python :: 3.9
Classifier: Programming Language :: Python :: 3.10
Classifier: Programming Language :: Python :: 3.11
Classifier: Programming Language :: Python :: 3.12
Classifier: Programming Language :: Python :: 3.13
Classifier: Programming Language :: Python :: Implementation :: CPython
Classifier: Programming Language :: Python :: Implementation :: PyPy
Classifier: Programming Language :: Python
Classifier: Natural Language :: English
Classifier: Operating System :: OS Independent
Classifier: Topic :: Internet :: WWW/HTTP
Classifier: Framework :: Zope :: 3
Requires-Python: >=3.9
License-File: LICENSE.txt
Requires-Dist: setuptools
Requires-Dist: zope.browserpage
Requires-Dist: zope.component
Requires-Dist: zope.configuration>=4.2.0
Requires-Dist: zope.interface
Requires-Dist: zope.pagetemplate
Requires-Dist: zope.publisher
Requires-Dist: zope.schema
Provides-Extra: test
Requires-Dist: chameleon>=3.0; extra == "test"
Requires-Dist: z3c.pt>=3.1.0; extra == "test"
Requires-Dist: z3c.ptcompat>=2.1.0; extra == "test"
Requires-Dist: zope.testing; extra == "test"
Requires-Dist: zope.testrunner>=6.4; extra == "test"
Requires-Dist: zope.traversing; extra == "test"
Provides-Extra: chameleon
Requires-Dist: chameleon>=3.0; extra == "chameleon"
Requires-Dist: z3c.pt>=3.1.0; extra == "chameleon"
Requires-Dist: z3c.ptcompat>=2.1.0; extra == "chameleon"
Dynamic: author
Dynamic: author-email
Dynamic: classifier
Dynamic: description
Dynamic: home-page
Dynamic: keywords
Dynamic: license
Dynamic: provides-extra
Dynamic: requires-dist
Dynamic: requires-python
Dynamic: summary
